{
    "variants": {
        "type=bottom": [ 
        	{ "model": "minecraft:block/crimson_slab" },
        	{ "model": "minecraft:block/crimson_slab2" },
       		{ "model": "minecraft:block/crimson_slab3" },
        	{ "model": "minecraft:block/crimson_slab4" }
        ],
        "type=top": [ 
        	{ "model": "minecraft:block/crimson_slab_top" },
        	{ "model": "minecraft:block/crimson_slab_top2" },
        	{ "model": "minecraft:block/crimson_slab_top3" },
        	{ "model": "minecraft:block/crimson_slab_top4" } 
        ],
        "type=double": [ 
        	{ "model": "minecraft:block/crimson_planks" }, 
        	{ "model": "minecraft:block/crimson_planks2" }, 
        	{ "model": "minecraft:block/crimson_planks3" }, 
        	{ "model": "minecraft:block/crimson_planks4" }
       ]
    }
}
